django_htmx_modal_forms/__init__.py
django_htmx_modal_forms/apps.py
django_htmx_modal_forms/conf.py
django_htmx_modal_forms/main.py
django_htmx_modal_forms/py.typed
django_htmx_modal_forms/views.py
django_htmx_modal_forms/migrations/__init__.py
django_htmx_modal_forms/static/htmx_modal_forms/js/modal-handlers.js
django_htmx_modal_forms/templates/htmx_modal_forms/_form_content.html
django_htmx_modal_forms/templates/htmx_modal_forms/_modal_form.html
django_htmx_modal_forms/templatetags/__init__.py
django_htmx_modal_forms/templatetags/htmx_modal_forms.py
django_htmx_modal_forms-0.4.0.dist-info/licenses/LICENSE
django_htmx_modal_forms-0.4.0.dist-info/METADATA
django_htmx_modal_forms-0.4.0.dist-info/WHEEL
django_htmx_modal_forms-0.4.0.dist-info/top_level.txt
django_htmx_modal_forms-0.4.0.dist-info/RECORD
