Metadata-Version: 2.4
Name: django-htmx-modal-forms
Version: 0.4.0
Summary: Django class-based views for HTMX-powered Bootstrap modals
Author-email: Abe Hanoka <abe@habet.dev>
License: MIT
Project-URL: Bug Tracker, https://github.com/abe-101/django-htmx-modal-forms/issues
Project-URL: Changelog, https://github.com/abe-101/django-htmx-modal-forms/blob/main/CHANGELOG.md
Project-URL: documentation, https://django-htmx-modal-forms.readthedocs.io
Project-URL: repository, https://github.com/abe-101/django-htmx-modal-forms
Classifier: Development Status :: 2 - Pre-Alpha
Classifier: Intended Audience :: Developers
Classifier: Natural Language :: English
Classifier: Operating System :: OS Independent
Classifier: Framework :: Django
Classifier: Framework :: Django :: 4.2
Classifier: Framework :: Django :: 5.0
Classifier: Framework :: Django :: 5.1
Classifier: Programming Language :: Python :: 3.9
Classifier: Programming Language :: Python :: 3.10
Classifier: Programming Language :: Python :: 3.11
Classifier: Programming Language :: Python :: 3.12
Classifier: Programming Language :: Python :: 3.13
Classifier: Topic :: Software Development :: Libraries
Requires-Python: >=3.9
License-File: LICENSE
Requires-Dist: django-crispy-forms>=2.3
Requires-Dist: django>=4.2
Requires-Dist: crispy-bootstrap5>=2024.10
Requires-Dist: django-htmx>=1.21.0
Dynamic: license-file
